pipeline/__init__.py
pipeline/pipeline.py
2404_segmentation_pipeline-1.0.0.dist-info/METADATA
2404_segmentation_pipeline-1.0.0.dist-info/WHEEL
2404_segmentation_pipeline-1.0.0.dist-info/top_level.txt
2404_segmentation_pipeline-1.0.0.dist-info/RECORD
