Metadata-Version: 2.1
Name: 2404-segmentation-pipeline
Version: 1.0.0
Summary: UNKNOWN
Home-page: https://github.com/2404-Organ-Segmentation/segmentation-pipeline
Author: 2404 Organ Segmentation
Author-email: joey.xiang426@gmail.com
License: MIT
Platform: UNKNOWN
Requires-Dist: monai (==1.3.0)
Requires-Dist: nibabel (==5.2.0)
Requires-Dist: matplotlib (==3.8.2)
Requires-Dist: tensorboard (==2.15.1)
Requires-Dist: tqdm (==4.66.1)
Requires-Dist: scipy (==1.12.0)
Requires-Dist: numpy (==1.24.1)
Requires-Dist: einops (==0.7.0)
Requires-Dist: scikit-image (==0.22.0)
